traceme/__init__.py
traceme/_version.py
traceme/py.typed
traceme/traceme.py
traceme-0.6.0.dist-info/LICENSE
traceme-0.6.0.dist-info/METADATA
traceme-0.6.0.dist-info/WHEEL
traceme-0.6.0.dist-info/RECORD
