Metadata-Version: 2.1
Name: traceme
Version: 0.6.0
Summary: Python debug and tracer library
Author: Dag Brattli
Author-email: dag@brattli.net
Requires-Python: >=3.10,<4.0
Classifier: Programming Language :: Python :: 3
Classifier: Programming Language :: Python :: 3.10
Classifier: Programming Language :: Python :: 3.11
Classifier: Programming Language :: Python :: 3.12
Requires-Dist: colorama (>=0.4.6,<0.5.0)
Requires-Dist: rich (>=13.7.0,<14.0.0)
Requires-Dist: structlog (>=24.1.0,<25.0.0)
